avalia_temperatura/__init__.py
avalia_temperatura/termometro.py
avalia_temperatura-0.0.3.dist-info/METADATA
avalia_temperatura-0.0.3.dist-info/WHEEL
avalia_temperatura-0.0.3.dist-info/top_level.txt
avalia_temperatura-0.0.3.dist-info/RECORD
