Metadata-Version: 2.1
Name: avalia-temperatura
Version: 0.0.3
Summary: Este pacote é um exercício do Desafio de Projeto da DIO
Home-page: https://github.com/GabeGD/Bootcamp_Geracao_Tech_Unimed_BH_Ciencia_de_Dados/pacote_DIO
Author: Gabriel
Requires-Python: >=3.7.15
